firebmail/__init__.py
firebmail/main.py
firebmail-0.1.7.dist-info/LICENSE.md
firebmail-0.1.7.dist-info/METADATA
firebmail-0.1.7.dist-info/WHEEL
firebmail-0.1.7.dist-info/top_level.txt
firebmail-0.1.7.dist-info/RECORD
