Metadata-Version: 2.1
Name: firebmail
Version: 0.1.7
Summary: An email sending utility for python
Author-email: lordfirebcorps@gmail.com
Project-URL: Homepage, https://github.com/firebreather-heart/firebmail
Project-URL: Issues, https://github.com/firebreather-heart/firebmail/issues
Classifier: Programming Language :: Python :: 3
Classifier: License :: OSI Approved :: MIT License
Classifier: Operating System :: OS Independent
Requires-Python: >=3.8
License-File: LICENSE.md
